package com.auditude.ads.util;

class PingUtil$1
  implements Runnable
{
  PingUtil$1(int paramInt, String paramString1, String paramString2) {}
  
  /* Error */
  public void run()
  {
    // Byte code:
    //   0: iconst_0
    //   1: istore_1
    //   2: iconst_0
    //   3: istore 7
    //   5: iconst_0
    //   6: istore 8
    //   8: iconst_0
    //   9: istore 9
    //   11: iconst_0
    //   12: istore 10
    //   14: iconst_0
    //   15: istore 6
    //   17: aconst_null
    //   18: astore 21
    //   20: aconst_null
    //   21: astore 20
    //   23: ldc 32
    //   25: astore 13
    //   27: aload 13
    //   29: astore 16
    //   31: iload 7
    //   33: istore_3
    //   34: aload 13
    //   36: astore 17
    //   38: iload 8
    //   40: istore 4
    //   42: aload_0
    //   43: getfield 17	com/auditude/ads/util/PingUtil$1:val$url	Ljava/lang/String;
    //   46: invokestatic 38	com/auditude/ads/util/PingUtil:access$0	(Ljava/lang/String;)Ljava/net/HttpURLConnection;
    //   49: astore 15
    //   51: aload 13
    //   53: astore 16
    //   55: iload 7
    //   57: istore_3
    //   58: aload 15
    //   60: astore 20
    //   62: aload 13
    //   64: astore 17
    //   66: iload 8
    //   68: istore 4
    //   70: aload 15
    //   72: astore 21
    //   74: aload 13
    //   76: astore 14
    //   78: iload 9
    //   80: istore_2
    //   81: aload 15
    //   83: astore 19
    //   85: aload 13
    //   87: astore 18
    //   89: iload 10
    //   91: istore 5
    //   93: aload 15
    //   95: iconst_0
    //   96: invokevirtual 44	java/net/HttpURLConnection:setInstanceFollowRedirects	(Z)V
    //   99: aload 13
    //   101: astore 12
    //   103: aload 15
    //   105: ifnull +693 -> 798
    //   108: aload 13
    //   110: astore 16
    //   112: iload 7
    //   114: istore_3
    //   115: aload 15
    //   117: astore 20
    //   119: aload 13
    //   121: astore 17
    //   123: iload 8
    //   125: istore 4
    //   127: aload 15
    //   129: astore 21
    //   131: aload 13
    //   133: astore 14
    //   135: iload 9
    //   137: istore_2
    //   138: aload 15
    //   140: astore 19
    //   142: aload 13
    //   144: astore 18
    //   146: iload 10
    //   148: istore 5
    //   150: aload 15
    //   152: ldc 46
    //   154: invokevirtual 50	java/net/HttpURLConnection:setRequestMethod	(Ljava/lang/String;)V
    //   157: aload 13
    //   159: astore 16
    //   161: iload 7
    //   163: istore_3
    //   164: aload 15
    //   166: astore 20
    //   168: aload 13
    //   170: astore 17
    //   172: iload 8
    //   174: istore 4
    //   176: aload 15
    //   178: astore 21
    //   180: aload 13
    //   182: astore 14
    //   184: iload 9
    //   186: istore_2
    //   187: aload 15
    //   189: astore 19
    //   191: aload 13
    //   193: astore 18
    //   195: iload 10
    //   197: istore 5
    //   199: aload 15
    //   201: invokestatic 54	com/auditude/ads/util/PingUtil:access$1	()Ljava/lang/Integer;
    //   204: invokevirtual 60	java/lang/Integer:intValue	()I
    //   207: invokevirtual 64	java/net/HttpURLConnection:setConnectTimeout	(I)V
    //   210: aload 13
    //   212: astore 16
    //   214: iload 7
    //   216: istore_3
    //   217: aload 15
    //   219: astore 20
    //   221: aload 13
    //   223: astore 17
    //   225: iload 8
    //   227: istore 4
    //   229: aload 15
    //   231: astore 21
    //   233: aload 13
    //   235: astore 14
    //   237: iload 9
    //   239: istore_2
    //   240: aload 15
    //   242: astore 19
    //   244: aload 13
    //   246: astore 18
    //   248: iload 10
    //   250: istore 5
    //   252: aload 15
    //   254: invokestatic 54	com/auditude/ads/util/PingUtil:access$1	()Ljava/lang/Integer;
    //   257: invokevirtual 60	java/lang/Integer:intValue	()I
    //   260: invokevirtual 67	java/net/HttpURLConnection:setReadTimeout	(I)V
    //   263: aload 13
    //   265: astore 16
    //   267: iload 7
    //   269: istore_3
    //   270: aload 15
    //   272: astore 20
    //   274: aload 13
    //   276: astore 17
    //   278: iload 8
    //   280: istore 4
    //   282: aload 15
    //   284: astore 21
    //   286: aload 13
    //   288: astore 14
    //   290: iload 9
    //   292: istore_2
    //   293: aload 15
    //   295: astore 19
    //   297: aload 13
    //   299: astore 18
    //   301: iload 10
    //   303: istore 5
    //   305: aload 15
    //   307: ldc 69
    //   309: aload_0
    //   310: getfield 19	com/auditude/ads/util/PingUtil$1:val$userAgent	Ljava/lang/String;
    //   313: invokevirtual 73	java/net/HttpURLConnection:setRequestProperty	(Ljava/lang/String;Ljava/lang/String;)V
    //   316: aload 13
    //   318: astore 16
    //   320: iload 7
    //   322: istore_3
    //   323: aload 15
    //   325: astore 20
    //   327: aload 13
    //   329: astore 17
    //   331: iload 8
    //   333: istore 4
    //   335: aload 15
    //   337: astore 21
    //   339: aload 13
    //   341: astore 14
    //   343: iload 9
    //   345: istore_2
    //   346: aload 15
    //   348: astore 19
    //   350: aload 13
    //   352: astore 18
    //   354: iload 10
    //   356: istore 5
    //   358: aload 15
    //   360: ldc 75
    //   362: ldc 77
    //   364: invokevirtual 73	java/net/HttpURLConnection:setRequestProperty	(Ljava/lang/String;Ljava/lang/String;)V
    //   367: aload 13
    //   369: astore 16
    //   371: iload 7
    //   373: istore_3
    //   374: aload 15
    //   376: astore 20
    //   378: aload 13
    //   380: astore 17
    //   382: iload 8
    //   384: istore 4
    //   386: aload 15
    //   388: astore 21
    //   390: aload 13
    //   392: astore 14
    //   394: iload 9
    //   396: istore_2
    //   397: aload 15
    //   399: astore 19
    //   401: aload 13
    //   403: astore 18
    //   405: iload 10
    //   407: istore 5
    //   409: aload 15
    //   411: invokevirtual 80	java/net/HttpURLConnection:connect	()V
    //   414: aload 13
    //   416: astore 16
    //   418: iload 7
    //   420: istore_3
    //   421: aload 15
    //   423: astore 20
    //   425: aload 13
    //   427: astore 17
    //   429: iload 8
    //   431: istore 4
    //   433: aload 15
    //   435: astore 21
    //   437: aload 13
    //   439: astore 14
    //   441: iload 9
    //   443: istore_2
    //   444: aload 15
    //   446: astore 19
    //   448: aload 13
    //   450: astore 18
    //   452: iload 10
    //   454: istore 5
    //   456: ldc 82
    //   458: invokestatic 88	com/auditude/ads/util/log/Log:getLogger	(Ljava/lang/String;)Lcom/auditude/ads/util/log/ILogger;
    //   461: new 90	java/lang/StringBuilder
    //   464: dup
    //   465: ldc 92
    //   467: invokespecial 94	java/lang/StringBuilder:<init>	(Ljava/lang/String;)V
    //   470: aload_0
    //   471: getfield 15	com/auditude/ads/util/PingUtil$1:val$redirect	I
    //   474: invokevirtual 98	java/lang/StringBuilder:append	(I)Ljava/lang/StringBuilder;
    //   477: ldc 100
    //   479: invokevirtual 103	java/lang/StringBuilder:append	(Ljava/lang/String;)Ljava/lang/StringBuilder;
    //   482: aload_0
    //   483: getfield 17	com/auditude/ads/util/PingUtil$1:val$url	Ljava/lang/String;
    //   486: invokevirtual 103	java/lang/StringBuilder:append	(Ljava/lang/String;)Ljava/lang/StringBuilder;
    //   489: invokevirtual 107	java/lang/StringBuilder:toString	()Ljava/lang/String;
    //   492: invokeinterface 113 2 0
    //   497: aload 13
    //   499: astore 16
    //   501: iload 7
    //   503: istore_3
    //   504: aload 15
    //   506: astore 20
    //   508: aload 13
    //   510: astore 17
    //   512: iload 8
    //   514: istore 4
    //   516: aload 15
    //   518: astore 21
    //   520: aload 13
    //   522: astore 14
    //   524: iload 9
    //   526: istore_2
    //   527: aload 15
    //   529: astore 19
    //   531: aload 13
    //   533: astore 18
    //   535: iload 10
    //   537: istore 5
    //   539: aload 15
    //   541: invokevirtual 116	java/net/HttpURLConnection:getResponseCode	()I
    //   544: istore 11
    //   546: iload 11
    //   548: sipush 302
    //   551: if_icmpeq +18 -> 569
    //   554: aload 13
    //   556: astore 12
    //   558: iload 6
    //   560: istore_1
    //   561: iload 11
    //   563: sipush 301
    //   566: if_icmpne +186 -> 752
    //   569: aload 13
    //   571: astore 16
    //   573: iload 7
    //   575: istore_3
    //   576: aload 15
    //   578: astore 20
    //   580: aload 13
    //   582: astore 17
    //   584: iload 8
    //   586: istore 4
    //   588: aload 15
    //   590: astore 21
    //   592: aload 13
    //   594: astore 14
    //   596: iload 9
    //   598: istore_2
    //   599: aload 15
    //   601: astore 19
    //   603: aload 13
    //   605: astore 18
    //   607: iload 10
    //   609: istore 5
    //   611: aload_0
    //   612: getfield 17	com/auditude/ads/util/PingUtil$1:val$url	Ljava/lang/String;
    //   615: aload 15
    //   617: ldc 118
    //   619: invokevirtual 122	java/net/HttpURLConnection:getHeaderField	(Ljava/lang/String;)Ljava/lang/String;
    //   622: invokestatic 126	com/auditude/ads/util/PingUtil:access$2	(Ljava/lang/String;Ljava/lang/String;)Ljava/lang/String;
    //   625: astore 13
    //   627: aload 13
    //   629: astore 12
    //   631: iload 6
    //   633: istore_1
    //   634: aload 13
    //   636: astore 16
    //   638: iload 7
    //   640: istore_3
    //   641: aload 15
    //   643: astore 20
    //   645: aload 13
    //   647: astore 17
    //   649: iload 8
    //   651: istore 4
    //   653: aload 15
    //   655: astore 21
    //   657: aload 13
    //   659: astore 14
    //   661: iload 9
    //   663: istore_2
    //   664: aload 15
    //   666: astore 19
    //   668: aload 13
    //   670: astore 18
    //   672: iload 10
    //   674: istore 5
    //   676: aload 13
    //   678: invokevirtual 131	java/lang/String:length	()I
    //   681: ifle +71 -> 752
    //   684: aload 13
    //   686: astore 12
    //   688: iload 6
    //   690: istore_1
    //   691: aload 13
    //   693: astore 16
    //   695: iload 7
    //   697: istore_3
    //   698: aload 15
    //   700: astore 20
    //   702: aload 13
    //   704: astore 17
    //   706: iload 8
    //   708: istore 4
    //   710: aload 15
    //   712: astore 21
    //   714: aload 13
    //   716: astore 14
    //   718: iload 9
    //   720: istore_2
    //   721: aload 15
    //   723: astore 19
    //   725: aload 13
    //   727: astore 18
    //   729: iload 10
    //   731: istore 5
    //   733: aload 13
    //   735: invokevirtual 134	java/lang/String:toLowerCase	()Ljava/lang/String;
    //   738: ldc -120
    //   740: invokevirtual 140	java/lang/String:startsWith	(Ljava/lang/String;)Z
    //   743: ifeq +9 -> 752
    //   746: iconst_1
    //   747: istore_1
    //   748: aload 13
    //   750: astore 12
    //   752: aload 12
    //   754: astore 16
    //   756: iload_1
    //   757: istore_3
    //   758: aload 15
    //   760: astore 20
    //   762: aload 12
    //   764: astore 17
    //   766: iload_1
    //   767: istore 4
    //   769: aload 15
    //   771: astore 21
    //   773: aload 12
    //   775: astore 14
    //   777: iload_1
    //   778: istore_2
    //   779: aload 15
    //   781: astore 19
    //   783: aload 12
    //   785: astore 18
    //   787: iload_1
    //   788: istore 5
    //   790: aload 15
    //   792: invokevirtual 144	java/net/HttpURLConnection:getInputStream	()Ljava/io/InputStream;
    //   795: invokevirtual 148	java/io/InputStream:close	()V
    //   798: aload 15
    //   800: ifnull +8 -> 808
    //   803: aload 15
    //   805: invokevirtual 151	java/net/HttpURLConnection:disconnect	()V
    //   808: iload_1
    //   809: ifeq +53 -> 862
    //   812: ldc 82
    //   814: invokestatic 88	com/auditude/ads/util/log/Log:getLogger	(Ljava/lang/String;)Lcom/auditude/ads/util/log/ILogger;
    //   817: new 90	java/lang/StringBuilder
    //   820: dup
    //   821: ldc -103
    //   823: invokespecial 94	java/lang/StringBuilder:<init>	(Ljava/lang/String;)V
    //   826: aload_0
    //   827: getfield 15	com/auditude/ads/util/PingUtil$1:val$redirect	I
    //   830: invokevirtual 98	java/lang/StringBuilder:append	(I)Ljava/lang/StringBuilder;
    //   833: ldc 100
    //   835: invokevirtual 103	java/lang/StringBuilder:append	(Ljava/lang/String;)Ljava/lang/StringBuilder;
    //   838: aload 12
    //   840: invokevirtual 103	java/lang/StringBuilder:append	(Ljava/lang/String;)Ljava/lang/StringBuilder;
    //   843: invokevirtual 107	java/lang/StringBuilder:toString	()Ljava/lang/String;
    //   846: invokeinterface 113 2 0
    //   851: aload 12
    //   853: aload_0
    //   854: getfield 15	com/auditude/ads/util/PingUtil$1:val$redirect	I
    //   857: iconst_1
    //   858: iadd
    //   859: invokestatic 157	com/auditude/ads/util/PingUtil:pingUrl	(Ljava/lang/String;I)V
    //   862: return
    //   863: astore 12
    //   865: aload 16
    //   867: astore 14
    //   869: iload_3
    //   870: istore_2
    //   871: aload 20
    //   873: astore 19
    //   875: ldc 82
    //   877: invokestatic 88	com/auditude/ads/util/log/Log:getLogger	(Ljava/lang/String;)Lcom/auditude/ads/util/log/ILogger;
    //   880: new 90	java/lang/StringBuilder
    //   883: dup
    //   884: ldc -97
    //   886: invokespecial 94	java/lang/StringBuilder:<init>	(Ljava/lang/String;)V
    //   889: aload_0
    //   890: getfield 17	com/auditude/ads/util/PingUtil$1:val$url	Ljava/lang/String;
    //   893: invokevirtual 103	java/lang/StringBuilder:append	(Ljava/lang/String;)Ljava/lang/StringBuilder;
    //   896: invokevirtual 107	java/lang/StringBuilder:toString	()Ljava/lang/String;
    //   899: invokeinterface 113 2 0
    //   904: aload 20
    //   906: ifnull +8 -> 914
    //   909: aload 20
    //   911: invokevirtual 151	java/net/HttpURLConnection:disconnect	()V
    //   914: iload_3
    //   915: ifeq -53 -> 862
    //   918: ldc 82
    //   920: invokestatic 88	com/auditude/ads/util/log/Log:getLogger	(Ljava/lang/String;)Lcom/auditude/ads/util/log/ILogger;
    //   923: new 90	java/lang/StringBuilder
    //   926: dup
    //   927: ldc -103
    //   929: invokespecial 94	java/lang/StringBuilder:<init>	(Ljava/lang/String;)V
    //   932: aload_0
    //   933: getfield 15	com/auditude/ads/util/PingUtil$1:val$redirect	I
    //   936: invokevirtual 98	java/lang/StringBuilder:append	(I)Ljava/lang/StringBuilder;
    //   939: ldc 100
    //   941: invokevirtual 103	java/lang/StringBuilder:append	(Ljava/lang/String;)Ljava/lang/StringBuilder;
    //   944: aload 16
    //   946: invokevirtual 103	java/lang/StringBuilder:append	(Ljava/lang/String;)Ljava/lang/StringBuilder;
    //   949: invokevirtual 107	java/lang/StringBuilder:toString	()Ljava/lang/String;
    //   952: invokeinterface 113 2 0
    //   957: aload 16
    //   959: aload_0
    //   960: getfield 15	com/auditude/ads/util/PingUtil$1:val$redirect	I
    //   963: iconst_1
    //   964: iadd
    //   965: invokestatic 157	com/auditude/ads/util/PingUtil:pingUrl	(Ljava/lang/String;I)V
    //   968: return
    //   969: astore 14
    //   971: aconst_null
    //   972: astore 12
    //   974: iconst_0
    //   975: istore_1
    //   976: ldc 32
    //   978: astore 13
    //   980: ldc 82
    //   982: invokestatic 88	com/auditude/ads/util/log/Log:getLogger	(Ljava/lang/String;)Lcom/auditude/ads/util/log/ILogger;
    //   985: new 90	java/lang/StringBuilder
    //   988: dup
    //   989: ldc -95
    //   991: invokespecial 94	java/lang/StringBuilder:<init>	(Ljava/lang/String;)V
    //   994: aload 14
    //   996: invokevirtual 164	java/io/IOException:getLocalizedMessage	()Ljava/lang/String;
    //   999: invokevirtual 103	java/lang/StringBuilder:append	(Ljava/lang/String;)Ljava/lang/StringBuilder;
    //   1002: ldc -90
    //   1004: invokevirtual 103	java/lang/StringBuilder:append	(Ljava/lang/String;)Ljava/lang/StringBuilder;
    //   1007: invokevirtual 107	java/lang/StringBuilder:toString	()Ljava/lang/String;
    //   1010: invokeinterface 113 2 0
    //   1015: aload 12
    //   1017: ifnull +8 -> 1025
    //   1020: aload 12
    //   1022: invokevirtual 151	java/net/HttpURLConnection:disconnect	()V
    //   1025: iload_1
    //   1026: ifeq -164 -> 862
    //   1029: ldc 82
    //   1031: invokestatic 88	com/auditude/ads/util/log/Log:getLogger	(Ljava/lang/String;)Lcom/auditude/ads/util/log/ILogger;
    //   1034: new 90	java/lang/StringBuilder
    //   1037: dup
    //   1038: ldc -103
    //   1040: invokespecial 94	java/lang/StringBuilder:<init>	(Ljava/lang/String;)V
    //   1043: aload_0
    //   1044: getfield 15	com/auditude/ads/util/PingUtil$1:val$redirect	I
    //   1047: invokevirtual 98	java/lang/StringBuilder:append	(I)Ljava/lang/StringBuilder;
    //   1050: ldc 100
    //   1052: invokevirtual 103	java/lang/StringBuilder:append	(Ljava/lang/String;)Ljava/lang/StringBuilder;
    //   1055: aload 13
    //   1057: invokevirtual 103	java/lang/StringBuilder:append	(Ljava/lang/String;)Ljava/lang/StringBuilder;
    //   1060: invokevirtual 107	java/lang/StringBuilder:toString	()Ljava/lang/String;
    //   1063: invokeinterface 113 2 0
    //   1068: aload 13
    //   1070: aload_0
    //   1071: getfield 15	com/auditude/ads/util/PingUtil$1:val$redirect	I
    //   1074: iconst_1
    //   1075: iadd
    //   1076: invokestatic 157	com/auditude/ads/util/PingUtil:pingUrl	(Ljava/lang/String;I)V
    //   1079: return
    //   1080: astore 12
    //   1082: aload 17
    //   1084: astore 14
    //   1086: iload 4
    //   1088: istore_2
    //   1089: aload 21
    //   1091: astore 19
    //   1093: ldc 82
    //   1095: invokestatic 88	com/auditude/ads/util/log/Log:getLogger	(Ljava/lang/String;)Lcom/auditude/ads/util/log/ILogger;
    //   1098: new 90	java/lang/StringBuilder
    //   1101: dup
    //   1102: ldc -88
    //   1104: invokespecial 94	java/lang/StringBuilder:<init>	(Ljava/lang/String;)V
    //   1107: aload_0
    //   1108: getfield 17	com/auditude/ads/util/PingUtil$1:val$url	Ljava/lang/String;
    //   1111: invokevirtual 103	java/lang/StringBuilder:append	(Ljava/lang/String;)Ljava/lang/StringBuilder;
    //   1114: invokevirtual 107	java/lang/StringBuilder:toString	()Ljava/lang/String;
    //   1117: invokeinterface 113 2 0
    //   1122: aload 21
    //   1124: ifnull +8 -> 1132
    //   1127: aload 21
    //   1129: invokevirtual 151	java/net/HttpURLConnection:disconnect	()V
    //   1132: iload 4
    //   1134: ifeq -272 -> 862
    //   1137: ldc 82
    //   1139: invokestatic 88	com/auditude/ads/util/log/Log:getLogger	(Ljava/lang/String;)Lcom/auditude/ads/util/log/ILogger;
    //   1142: new 90	java/lang/StringBuilder
    //   1145: dup
    //   1146: ldc -103
    //   1148: invokespecial 94	java/lang/StringBuilder:<init>	(Ljava/lang/String;)V
    //   1151: aload_0
    //   1152: getfield 15	com/auditude/ads/util/PingUtil$1:val$redirect	I
    //   1155: invokevirtual 98	java/lang/StringBuilder:append	(I)Ljava/lang/StringBuilder;
    //   1158: ldc 100
    //   1160: invokevirtual 103	java/lang/StringBuilder:append	(Ljava/lang/String;)Ljava/lang/StringBuilder;
    //   1163: aload 17
    //   1165: invokevirtual 103	java/lang/StringBuilder:append	(Ljava/lang/String;)Ljava/lang/StringBuilder;
    //   1168: invokevirtual 107	java/lang/StringBuilder:toString	()Ljava/lang/String;
    //   1171: invokeinterface 113 2 0
    //   1176: aload 17
    //   1178: aload_0
    //   1179: getfield 15	com/auditude/ads/util/PingUtil$1:val$redirect	I
    //   1182: iconst_1
    //   1183: iadd
    //   1184: invokestatic 157	com/auditude/ads/util/PingUtil:pingUrl	(Ljava/lang/String;I)V
    //   1187: return
    //   1188: astore 14
    //   1190: aconst_null
    //   1191: astore 12
    //   1193: iconst_0
    //   1194: istore_1
    //   1195: ldc 32
    //   1197: astore 13
    //   1199: aload 12
    //   1201: ifnull +8 -> 1209
    //   1204: aload 12
    //   1206: invokevirtual 151	java/net/HttpURLConnection:disconnect	()V
    //   1209: iload_1
    //   1210: ifeq +53 -> 1263
    //   1213: ldc 82
    //   1215: invokestatic 88	com/auditude/ads/util/log/Log:getLogger	(Ljava/lang/String;)Lcom/auditude/ads/util/log/ILogger;
    //   1218: new 90	java/lang/StringBuilder
    //   1221: dup
    //   1222: ldc -103
    //   1224: invokespecial 94	java/lang/StringBuilder:<init>	(Ljava/lang/String;)V
    //   1227: aload_0
    //   1228: getfield 15	com/auditude/ads/util/PingUtil$1:val$redirect	I
    //   1231: invokevirtual 98	java/lang/StringBuilder:append	(I)Ljava/lang/StringBuilder;
    //   1234: ldc 100
    //   1236: invokevirtual 103	java/lang/StringBuilder:append	(Ljava/lang/String;)Ljava/lang/StringBuilder;
    //   1239: aload 13
    //   1241: invokevirtual 103	java/lang/StringBuilder:append	(Ljava/lang/String;)Ljava/lang/StringBuilder;
    //   1244: invokevirtual 107	java/lang/StringBuilder:toString	()Ljava/lang/String;
    //   1247: invokeinterface 113 2 0
    //   1252: aload 13
    //   1254: aload_0
    //   1255: getfield 15	com/auditude/ads/util/PingUtil$1:val$redirect	I
    //   1258: iconst_1
    //   1259: iadd
    //   1260: invokestatic 157	com/auditude/ads/util/PingUtil:pingUrl	(Ljava/lang/String;I)V
    //   1263: aload 14
    //   1265: athrow
    //   1266: astore 15
    //   1268: aload 19
    //   1270: astore 12
    //   1272: iload_2
    //   1273: istore_1
    //   1274: aload 14
    //   1276: astore 13
    //   1278: aload 15
    //   1280: astore 14
    //   1282: goto -83 -> 1199
    //   1285: astore 14
    //   1287: goto -88 -> 1199
    //   1290: astore 14
    //   1292: aload 15
    //   1294: astore 12
    //   1296: iload 5
    //   1298: istore_1
    //   1299: aload 18
    //   1301: astore 13
    //   1303: goto -323 -> 980
    // Local variable table:
    //   start	length	slot	name	signature
    //   0	1306	0	this	1
    //   1	1298	1	i	int
    //   80	1193	2	j	int
    //   33	882	3	k	int
    //   40	1093	4	m	int
    //   91	1206	5	n	int
    //   15	674	6	i1	int
    //   3	693	7	i2	int
    //   6	701	8	i3	int
    //   9	710	9	i4	int
    //   12	718	10	i5	int
    //   544	23	11	i6	int
    //   101	751	12	localObject1	Object
    //   863	1	12	localSocketTimeoutException	java.net.SocketTimeoutException
    //   972	49	12	localObject2	Object
    //   1080	1	12	localException	Exception
    //   1191	104	12	localObject3	Object
    //   25	1277	13	localObject4	Object
    //   76	792	14	localObject5	Object
    //   969	26	14	localIOException1	java.io.IOException
    //   1084	1	14	localObject6	Object
    //   1188	87	14	localObject7	Object
    //   1280	1	14	localObject8	Object
    //   1285	1	14	localObject9	Object
    //   1290	1	14	localIOException2	java.io.IOException
    //   49	755	15	localHttpURLConnection	java.net.HttpURLConnection
    //   1266	27	15	localObject10	Object
    //   29	929	16	localObject11	Object
    //   36	1141	17	localObject12	Object
    //   87	1213	18	localObject13	Object
    //   83	1186	19	localObject14	Object
    //   21	889	20	localObject15	Object
    //   18	1110	21	localObject16	Object
    // Exception table:
    //   from	to	target	type
    //   42	51	863	java/net/SocketTimeoutException
    //   93	99	863	java/net/SocketTimeoutException
    //   150	157	863	java/net/SocketTimeoutException
    //   199	210	863	java/net/SocketTimeoutException
    //   252	263	863	java/net/SocketTimeoutException
    //   305	316	863	java/net/SocketTimeoutException
    //   358	367	863	java/net/SocketTimeoutException
    //   409	414	863	java/net/SocketTimeoutException
    //   456	497	863	java/net/SocketTimeoutException
    //   539	546	863	java/net/SocketTimeoutException
    //   611	627	863	java/net/SocketTimeoutException
    //   676	684	863	java/net/SocketTimeoutException
    //   733	746	863	java/net/SocketTimeoutException
    //   790	798	863	java/net/SocketTimeoutException
    //   42	51	969	java/io/IOException
    //   42	51	1080	java/lang/Exception
    //   93	99	1080	java/lang/Exception
    //   150	157	1080	java/lang/Exception
    //   199	210	1080	java/lang/Exception
    //   252	263	1080	java/lang/Exception
    //   305	316	1080	java/lang/Exception
    //   358	367	1080	java/lang/Exception
    //   409	414	1080	java/lang/Exception
    //   456	497	1080	java/lang/Exception
    //   539	546	1080	java/lang/Exception
    //   611	627	1080	java/lang/Exception
    //   676	684	1080	java/lang/Exception
    //   733	746	1080	java/lang/Exception
    //   790	798	1080	java/lang/Exception
    //   42	51	1188	finally
    //   93	99	1266	finally
    //   150	157	1266	finally
    //   199	210	1266	finally
    //   252	263	1266	finally
    //   305	316	1266	finally
    //   358	367	1266	finally
    //   409	414	1266	finally
    //   456	497	1266	finally
    //   539	546	1266	finally
    //   611	627	1266	finally
    //   676	684	1266	finally
    //   733	746	1266	finally
    //   790	798	1266	finally
    //   875	904	1266	finally
    //   1093	1122	1266	finally
    //   980	1015	1285	finally
    //   93	99	1290	java/io/IOException
    //   150	157	1290	java/io/IOException
    //   199	210	1290	java/io/IOException
    //   252	263	1290	java/io/IOException
    //   305	316	1290	java/io/IOException
    //   358	367	1290	java/io/IOException
    //   409	414	1290	java/io/IOException
    //   456	497	1290	java/io/IOException
    //   539	546	1290	java/io/IOException
    //   611	627	1290	java/io/IOException
    //   676	684	1290	java/io/IOException
    //   733	746	1290	java/io/IOException
    //   790	798	1290	java/io/IOException
  }
}

/* Location:
 * Qualified Name:     com.auditude.ads.util.PingUtil.1
 * Java Class Version: 6 (50.0)
 * JD-Core Version:    0.7.1
 */