package com.adobe.primetime.core;

class URLLoader$1
  implements Runnable
{
  URLLoader$1(URLLoader paramURLLoader, URLLoader.URLRequest paramURLRequest) {}
  
  /* Error */
  public void run()
  {
    // Byte code:
    //   0: aconst_null
    //   1: astore 6
    //   3: aconst_null
    //   4: astore 5
    //   6: aload_0
    //   7: getfield 14	com/adobe/primetime/core/URLLoader$1:this$0	Lcom/adobe/primetime/core/URLLoader;
    //   10: aload_0
    //   11: getfield 16	com/adobe/primetime/core/URLLoader$1:val$request	Lcom/adobe/primetime/core/URLLoader$URLRequest;
    //   14: invokevirtual 33	com/adobe/primetime/core/URLLoader$URLRequest:getUrl	()Ljava/lang/String;
    //   17: invokestatic 39	com/adobe/primetime/core/URLLoader:access$000	(Lcom/adobe/primetime/core/URLLoader;Ljava/lang/String;)Ljava/net/HttpURLConnection;
    //   20: astore_3
    //   21: aload_3
    //   22: ifnull +427 -> 449
    //   25: aload_3
    //   26: astore 5
    //   28: aload_3
    //   29: astore 6
    //   31: aload_3
    //   32: astore 4
    //   34: aload_3
    //   35: aload_0
    //   36: getfield 16	com/adobe/primetime/core/URLLoader$1:val$request	Lcom/adobe/primetime/core/URLLoader$URLRequest;
    //   39: invokevirtual 43	com/adobe/primetime/core/URLLoader$URLRequest:getMethod	()Lcom/adobe/primetime/core/URLLoader$HttpMethod;
    //   42: invokevirtual 48	com/adobe/primetime/core/URLLoader$HttpMethod:toString	()Ljava/lang/String;
    //   45: invokevirtual 54	java/net/HttpURLConnection:setRequestMethod	(Ljava/lang/String;)V
    //   48: aload_3
    //   49: astore 5
    //   51: aload_3
    //   52: astore 6
    //   54: aload_3
    //   55: astore 4
    //   57: aload_3
    //   58: invokestatic 58	com/adobe/primetime/core/URLLoader:access$100	()Ljava/lang/Integer;
    //   61: invokevirtual 64	java/lang/Integer:intValue	()I
    //   64: invokevirtual 68	java/net/HttpURLConnection:setConnectTimeout	(I)V
    //   67: aload_3
    //   68: astore 5
    //   70: aload_3
    //   71: astore 6
    //   73: aload_3
    //   74: astore 4
    //   76: aload_3
    //   77: invokestatic 58	com/adobe/primetime/core/URLLoader:access$100	()Ljava/lang/Integer;
    //   80: invokevirtual 64	java/lang/Integer:intValue	()I
    //   83: invokevirtual 71	java/net/HttpURLConnection:setReadTimeout	(I)V
    //   86: aload_3
    //   87: astore 5
    //   89: aload_3
    //   90: astore 6
    //   92: aload_3
    //   93: astore 4
    //   95: aload_3
    //   96: ldc 73
    //   98: invokestatic 76	com/adobe/primetime/core/URLLoader:getDefaultUserAgent	()Ljava/lang/String;
    //   101: invokevirtual 80	java/net/HttpURLConnection:setRequestProperty	(Ljava/lang/String;Ljava/lang/String;)V
    //   104: aload_3
    //   105: astore 5
    //   107: aload_3
    //   108: astore 6
    //   110: aload_3
    //   111: astore 4
    //   113: aload_3
    //   114: ldc 82
    //   116: ldc 84
    //   118: invokevirtual 80	java/net/HttpURLConnection:setRequestProperty	(Ljava/lang/String;Ljava/lang/String;)V
    //   121: aload_3
    //   122: astore 5
    //   124: aload_3
    //   125: astore 6
    //   127: aload_3
    //   128: astore 4
    //   130: aload_0
    //   131: getfield 16	com/adobe/primetime/core/URLLoader$1:val$request	Lcom/adobe/primetime/core/URLLoader$URLRequest;
    //   134: invokevirtual 43	com/adobe/primetime/core/URLLoader$URLRequest:getMethod	()Lcom/adobe/primetime/core/URLLoader$HttpMethod;
    //   137: getstatic 88	com/adobe/primetime/core/URLLoader$HttpMethod:POST	Lcom/adobe/primetime/core/URLLoader$HttpMethod;
    //   140: if_acmpne +104 -> 244
    //   143: aload_3
    //   144: astore 5
    //   146: aload_3
    //   147: astore 6
    //   149: aload_3
    //   150: astore 4
    //   152: aload_3
    //   153: ldc 90
    //   155: ldc 92
    //   157: invokevirtual 80	java/net/HttpURLConnection:setRequestProperty	(Ljava/lang/String;Ljava/lang/String;)V
    //   160: aload_3
    //   161: astore 5
    //   163: aload_3
    //   164: astore 6
    //   166: aload_3
    //   167: astore 4
    //   169: aload_0
    //   170: getfield 16	com/adobe/primetime/core/URLLoader$1:val$request	Lcom/adobe/primetime/core/URLLoader$URLRequest;
    //   173: invokevirtual 95	com/adobe/primetime/core/URLLoader$URLRequest:getUrlEncodedData	()Ljava/lang/String;
    //   176: astore 7
    //   178: aload_3
    //   179: astore 5
    //   181: aload_3
    //   182: astore 6
    //   184: aload_3
    //   185: astore 4
    //   187: new 97	java/io/DataOutputStream
    //   190: dup
    //   191: aload_3
    //   192: invokevirtual 101	java/net/HttpURLConnection:getOutputStream	()Ljava/io/OutputStream;
    //   195: invokespecial 104	java/io/DataOutputStream:<init>	(Ljava/io/OutputStream;)V
    //   198: astore 8
    //   200: aload_3
    //   201: astore 5
    //   203: aload_3
    //   204: astore 6
    //   206: aload_3
    //   207: astore 4
    //   209: aload 8
    //   211: aload 7
    //   213: invokevirtual 107	java/io/DataOutputStream:writeBytes	(Ljava/lang/String;)V
    //   216: aload_3
    //   217: astore 5
    //   219: aload_3
    //   220: astore 6
    //   222: aload_3
    //   223: astore 4
    //   225: aload 8
    //   227: invokevirtual 110	java/io/DataOutputStream:flush	()V
    //   230: aload_3
    //   231: astore 5
    //   233: aload_3
    //   234: astore 6
    //   236: aload_3
    //   237: astore 4
    //   239: aload 8
    //   241: invokevirtual 112	java/io/DataOutputStream:close	()V
    //   244: aload_3
    //   245: astore 5
    //   247: aload_3
    //   248: astore 6
    //   250: aload_3
    //   251: astore 4
    //   253: aload_3
    //   254: invokevirtual 115	java/net/HttpURLConnection:connect	()V
    //   257: aload_3
    //   258: astore 5
    //   260: aload_3
    //   261: astore 6
    //   263: aload_3
    //   264: astore 4
    //   266: aload_0
    //   267: getfield 14	com/adobe/primetime/core/URLLoader$1:this$0	Lcom/adobe/primetime/core/URLLoader;
    //   270: invokestatic 119	com/adobe/primetime/core/URLLoader:access$300	(Lcom/adobe/primetime/core/URLLoader;)Lcom/adobe/primetime/core/ILogger;
    //   273: aload_0
    //   274: getfield 14	com/adobe/primetime/core/URLLoader$1:this$0	Lcom/adobe/primetime/core/URLLoader;
    //   277: invokestatic 123	com/adobe/primetime/core/URLLoader:access$200	(Lcom/adobe/primetime/core/URLLoader;)Ljava/lang/String;
    //   280: new 125	java/lang/StringBuilder
    //   283: dup
    //   284: invokespecial 126	java/lang/StringBuilder:<init>	()V
    //   287: ldc -128
    //   289: invokevirtual 132	java/lang/StringBuilder:append	(Ljava/lang/String;)Ljava/lang/StringBuilder;
    //   292: aload_0
    //   293: getfield 16	com/adobe/primetime/core/URLLoader$1:val$request	Lcom/adobe/primetime/core/URLLoader$URLRequest;
    //   296: invokevirtual 33	com/adobe/primetime/core/URLLoader$URLRequest:getUrl	()Ljava/lang/String;
    //   299: invokevirtual 132	java/lang/StringBuilder:append	(Ljava/lang/String;)Ljava/lang/StringBuilder;
    //   302: invokevirtual 133	java/lang/StringBuilder:toString	()Ljava/lang/String;
    //   305: invokeinterface 138 3 0
    //   310: aload_3
    //   311: astore 5
    //   313: aload_3
    //   314: astore 6
    //   316: aload_3
    //   317: astore 4
    //   319: aload_3
    //   320: invokevirtual 142	java/net/HttpURLConnection:getInputStream	()Ljava/io/InputStream;
    //   323: astore 7
    //   325: aload_3
    //   326: astore 5
    //   328: aload_3
    //   329: astore 6
    //   331: aload_3
    //   332: astore 4
    //   334: aload_3
    //   335: invokevirtual 145	java/net/HttpURLConnection:getResponseCode	()I
    //   338: istore_1
    //   339: aload_3
    //   340: astore 5
    //   342: aload_3
    //   343: astore 6
    //   345: aload_3
    //   346: astore 4
    //   348: iload_1
    //   349: invokestatic 148	java/lang/Integer:toString	(I)Ljava/lang/String;
    //   352: iconst_0
    //   353: invokevirtual 154	java/lang/String:charAt	(I)C
    //   356: istore_2
    //   357: iload_2
    //   358: bipush 52
    //   360: if_icmpeq +9 -> 369
    //   363: iload_2
    //   364: bipush 53
    //   366: if_icmpne +92 -> 458
    //   369: aload_3
    //   370: astore 5
    //   372: aload_3
    //   373: astore 6
    //   375: aload_3
    //   376: astore 4
    //   378: aload_0
    //   379: getfield 14	com/adobe/primetime/core/URLLoader$1:this$0	Lcom/adobe/primetime/core/URLLoader;
    //   382: invokestatic 119	com/adobe/primetime/core/URLLoader:access$300	(Lcom/adobe/primetime/core/URLLoader;)Lcom/adobe/primetime/core/ILogger;
    //   385: aload_0
    //   386: getfield 14	com/adobe/primetime/core/URLLoader$1:this$0	Lcom/adobe/primetime/core/URLLoader;
    //   389: invokestatic 123	com/adobe/primetime/core/URLLoader:access$200	(Lcom/adobe/primetime/core/URLLoader;)Ljava/lang/String;
    //   392: new 125	java/lang/StringBuilder
    //   395: dup
    //   396: invokespecial 126	java/lang/StringBuilder:<init>	()V
    //   399: ldc -100
    //   401: invokevirtual 132	java/lang/StringBuilder:append	(Ljava/lang/String;)Ljava/lang/StringBuilder;
    //   404: iload_1
    //   405: invokevirtual 159	java/lang/StringBuilder:append	(I)Ljava/lang/StringBuilder;
    //   408: invokevirtual 133	java/lang/StringBuilder:toString	()Ljava/lang/String;
    //   411: invokeinterface 162 3 0
    //   416: aload_3
    //   417: astore 5
    //   419: aload_3
    //   420: astore 6
    //   422: aload_3
    //   423: astore 4
    //   425: aload 7
    //   427: invokevirtual 165	java/io/InputStream:close	()V
    //   430: aload_3
    //   431: astore 5
    //   433: aload_3
    //   434: astore 6
    //   436: aload_3
    //   437: astore 4
    //   439: aload_0
    //   440: getfield 14	com/adobe/primetime/core/URLLoader$1:this$0	Lcom/adobe/primetime/core/URLLoader;
    //   443: invokestatic 169	com/adobe/primetime/core/URLLoader:access$500	(Lcom/adobe/primetime/core/URLLoader;)Lcom/adobe/primetime/core/radio/Channel;
    //   446: invokevirtual 174	com/adobe/primetime/core/radio/Channel:shutdown	()V
    //   449: aload_3
    //   450: ifnull +7 -> 457
    //   453: aload_3
    //   454: invokevirtual 177	java/net/HttpURLConnection:disconnect	()V
    //   457: return
    //   458: aload_3
    //   459: astore 5
    //   461: aload_3
    //   462: astore 6
    //   464: aload_3
    //   465: astore 4
    //   467: aload_0
    //   468: getfield 14	com/adobe/primetime/core/URLLoader$1:this$0	Lcom/adobe/primetime/core/URLLoader;
    //   471: aload 7
    //   473: invokestatic 181	com/adobe/primetime/core/URLLoader:access$400	(Lcom/adobe/primetime/core/URLLoader;Ljava/io/InputStream;)Ljava/lang/String;
    //   476: astore 8
    //   478: aload_3
    //   479: astore 5
    //   481: aload_3
    //   482: astore 6
    //   484: aload_3
    //   485: astore 4
    //   487: new 183	java/util/HashMap
    //   490: dup
    //   491: invokespecial 184	java/util/HashMap:<init>	()V
    //   494: astore 9
    //   496: aload_3
    //   497: astore 5
    //   499: aload_3
    //   500: astore 6
    //   502: aload_3
    //   503: astore 4
    //   505: aload 9
    //   507: ldc -70
    //   509: aload 8
    //   511: invokeinterface 192 3 0
    //   516: pop
    //   517: aload_3
    //   518: astore 5
    //   520: aload_3
    //   521: astore 6
    //   523: aload_3
    //   524: astore 4
    //   526: aload_0
    //   527: getfield 14	com/adobe/primetime/core/URLLoader$1:this$0	Lcom/adobe/primetime/core/URLLoader;
    //   530: invokestatic 169	com/adobe/primetime/core/URLLoader:access$500	(Lcom/adobe/primetime/core/URLLoader;)Lcom/adobe/primetime/core/radio/Channel;
    //   533: new 194	com/adobe/primetime/core/Event
    //   536: dup
    //   537: ldc -60
    //   539: aload 9
    //   541: invokespecial 199	com/adobe/primetime/core/Event:<init>	(Ljava/lang/String;Ljava/lang/Object;)V
    //   544: invokevirtual 203	com/adobe/primetime/core/radio/Channel:trigger	(Lcom/adobe/primetime/core/Event;)V
    //   547: goto -131 -> 416
    //   550: astore_3
    //   551: aload 5
    //   553: astore 4
    //   555: aload_0
    //   556: getfield 14	com/adobe/primetime/core/URLLoader$1:this$0	Lcom/adobe/primetime/core/URLLoader;
    //   559: new 125	java/lang/StringBuilder
    //   562: dup
    //   563: invokespecial 126	java/lang/StringBuilder:<init>	()V
    //   566: ldc -51
    //   568: invokevirtual 132	java/lang/StringBuilder:append	(Ljava/lang/String;)Ljava/lang/StringBuilder;
    //   571: aload_0
    //   572: getfield 16	com/adobe/primetime/core/URLLoader$1:val$request	Lcom/adobe/primetime/core/URLLoader$URLRequest;
    //   575: invokevirtual 33	com/adobe/primetime/core/URLLoader$URLRequest:getUrl	()Ljava/lang/String;
    //   578: invokevirtual 132	java/lang/StringBuilder:append	(Ljava/lang/String;)Ljava/lang/StringBuilder;
    //   581: ldc -49
    //   583: invokevirtual 132	java/lang/StringBuilder:append	(Ljava/lang/String;)Ljava/lang/StringBuilder;
    //   586: invokevirtual 133	java/lang/StringBuilder:toString	()Ljava/lang/String;
    //   589: invokestatic 211	com/adobe/primetime/core/URLLoader:access$600	(Lcom/adobe/primetime/core/URLLoader;Ljava/lang/String;)V
    //   592: aload 5
    //   594: ifnull -137 -> 457
    //   597: aload 5
    //   599: invokevirtual 177	java/net/HttpURLConnection:disconnect	()V
    //   602: return
    //   603: astore 4
    //   605: aconst_null
    //   606: astore_3
    //   607: aload_0
    //   608: getfield 14	com/adobe/primetime/core/URLLoader$1:this$0	Lcom/adobe/primetime/core/URLLoader;
    //   611: new 125	java/lang/StringBuilder
    //   614: dup
    //   615: invokespecial 126	java/lang/StringBuilder:<init>	()V
    //   618: ldc -43
    //   620: invokevirtual 132	java/lang/StringBuilder:append	(Ljava/lang/String;)Ljava/lang/StringBuilder;
    //   623: aload 4
    //   625: invokevirtual 216	java/io/IOException:getLocalizedMessage	()Ljava/lang/String;
    //   628: invokevirtual 132	java/lang/StringBuilder:append	(Ljava/lang/String;)Ljava/lang/StringBuilder;
    //   631: ldc -49
    //   633: invokevirtual 132	java/lang/StringBuilder:append	(Ljava/lang/String;)Ljava/lang/StringBuilder;
    //   636: invokevirtual 133	java/lang/StringBuilder:toString	()Ljava/lang/String;
    //   639: invokestatic 211	com/adobe/primetime/core/URLLoader:access$600	(Lcom/adobe/primetime/core/URLLoader;Ljava/lang/String;)V
    //   642: aload_3
    //   643: ifnull -186 -> 457
    //   646: aload_3
    //   647: invokevirtual 177	java/net/HttpURLConnection:disconnect	()V
    //   650: return
    //   651: astore_3
    //   652: aload 6
    //   654: astore 4
    //   656: aload_0
    //   657: getfield 14	com/adobe/primetime/core/URLLoader$1:this$0	Lcom/adobe/primetime/core/URLLoader;
    //   660: ldc -38
    //   662: invokestatic 211	com/adobe/primetime/core/URLLoader:access$600	(Lcom/adobe/primetime/core/URLLoader;Ljava/lang/String;)V
    //   665: aload 6
    //   667: ifnull -210 -> 457
    //   670: aload 6
    //   672: invokevirtual 177	java/net/HttpURLConnection:disconnect	()V
    //   675: return
    //   676: astore 4
    //   678: aconst_null
    //   679: astore_3
    //   680: aload_3
    //   681: ifnull +7 -> 688
    //   684: aload_3
    //   685: invokevirtual 177	java/net/HttpURLConnection:disconnect	()V
    //   688: aload 4
    //   690: athrow
    //   691: astore 5
    //   693: aload 4
    //   695: astore_3
    //   696: aload 5
    //   698: astore 4
    //   700: goto -20 -> 680
    //   703: astore 4
    //   705: goto -25 -> 680
    //   708: astore 4
    //   710: goto -103 -> 607
    // Local variable table:
    //   start	length	slot	name	signature
    //   0	713	0	this	1
    //   338	67	1	i	int
    //   356	11	2	j	int
    //   20	504	3	localHttpURLConnection	java.net.HttpURLConnection
    //   550	1	3	localSocketTimeoutException	java.net.SocketTimeoutException
    //   606	41	3	localObject1	Object
    //   651	1	3	localException	Exception
    //   679	17	3	localObject2	Object
    //   32	522	4	localObject3	Object
    //   603	21	4	localIOException1	java.io.IOException
    //   654	1	4	localObject4	Object
    //   676	18	4	localObject5	Object
    //   698	1	4	localObject6	Object
    //   703	1	4	localObject7	Object
    //   708	1	4	localIOException2	java.io.IOException
    //   4	594	5	localObject8	Object
    //   691	6	5	localObject9	Object
    //   1	670	6	localObject10	Object
    //   176	296	7	localObject11	Object
    //   198	312	8	localObject12	Object
    //   494	46	9	localHashMap	java.util.HashMap
    // Exception table:
    //   from	to	target	type
    //   6	21	550	java/net/SocketTimeoutException
    //   34	48	550	java/net/SocketTimeoutException
    //   57	67	550	java/net/SocketTimeoutException
    //   76	86	550	java/net/SocketTimeoutException
    //   95	104	550	java/net/SocketTimeoutException
    //   113	121	550	java/net/SocketTimeoutException
    //   130	143	550	java/net/SocketTimeoutException
    //   152	160	550	java/net/SocketTimeoutException
    //   169	178	550	java/net/SocketTimeoutException
    //   187	200	550	java/net/SocketTimeoutException
    //   209	216	550	java/net/SocketTimeoutException
    //   225	230	550	java/net/SocketTimeoutException
    //   239	244	550	java/net/SocketTimeoutException
    //   253	257	550	java/net/SocketTimeoutException
    //   266	310	550	java/net/SocketTimeoutException
    //   319	325	550	java/net/SocketTimeoutException
    //   334	339	550	java/net/SocketTimeoutException
    //   348	357	550	java/net/SocketTimeoutException
    //   378	416	550	java/net/SocketTimeoutException
    //   425	430	550	java/net/SocketTimeoutException
    //   439	449	550	java/net/SocketTimeoutException
    //   467	478	550	java/net/SocketTimeoutException
    //   487	496	550	java/net/SocketTimeoutException
    //   505	517	550	java/net/SocketTimeoutException
    //   526	547	550	java/net/SocketTimeoutException
    //   6	21	603	java/io/IOException
    //   6	21	651	java/lang/Exception
    //   34	48	651	java/lang/Exception
    //   57	67	651	java/lang/Exception
    //   76	86	651	java/lang/Exception
    //   95	104	651	java/lang/Exception
    //   113	121	651	java/lang/Exception
    //   130	143	651	java/lang/Exception
    //   152	160	651	java/lang/Exception
    //   169	178	651	java/lang/Exception
    //   187	200	651	java/lang/Exception
    //   209	216	651	java/lang/Exception
    //   225	230	651	java/lang/Exception
    //   239	244	651	java/lang/Exception
    //   253	257	651	java/lang/Exception
    //   266	310	651	java/lang/Exception
    //   319	325	651	java/lang/Exception
    //   334	339	651	java/lang/Exception
    //   348	357	651	java/lang/Exception
    //   378	416	651	java/lang/Exception
    //   425	430	651	java/lang/Exception
    //   439	449	651	java/lang/Exception
    //   467	478	651	java/lang/Exception
    //   487	496	651	java/lang/Exception
    //   505	517	651	java/lang/Exception
    //   526	547	651	java/lang/Exception
    //   6	21	676	finally
    //   34	48	691	finally
    //   57	67	691	finally
    //   76	86	691	finally
    //   95	104	691	finally
    //   113	121	691	finally
    //   130	143	691	finally
    //   152	160	691	finally
    //   169	178	691	finally
    //   187	200	691	finally
    //   209	216	691	finally
    //   225	230	691	finally
    //   239	244	691	finally
    //   253	257	691	finally
    //   266	310	691	finally
    //   319	325	691	finally
    //   334	339	691	finally
    //   348	357	691	finally
    //   378	416	691	finally
    //   425	430	691	finally
    //   439	449	691	finally
    //   467	478	691	finally
    //   487	496	691	finally
    //   505	517	691	finally
    //   526	547	691	finally
    //   555	592	691	finally
    //   656	665	691	finally
    //   607	642	703	finally
    //   34	48	708	java/io/IOException
    //   57	67	708	java/io/IOException
    //   76	86	708	java/io/IOException
    //   95	104	708	java/io/IOException
    //   113	121	708	java/io/IOException
    //   130	143	708	java/io/IOException
    //   152	160	708	java/io/IOException
    //   169	178	708	java/io/IOException
    //   187	200	708	java/io/IOException
    //   209	216	708	java/io/IOException
    //   225	230	708	java/io/IOException
    //   239	244	708	java/io/IOException
    //   253	257	708	java/io/IOException
    //   266	310	708	java/io/IOException
    //   319	325	708	java/io/IOException
    //   334	339	708	java/io/IOException
    //   348	357	708	java/io/IOException
    //   378	416	708	java/io/IOException
    //   425	430	708	java/io/IOException
    //   439	449	708	java/io/IOException
    //   467	478	708	java/io/IOException
    //   487	496	708	java/io/IOException
    //   505	517	708	java/io/IOException
    //   526	547	708	java/io/IOException
  }
}

/* Location:
 * Qualified Name:     com.adobe.primetime.core.URLLoader.1
 * Java Class Version: 6 (50.0)
 * JD-Core Version:    0.7.1
 */